PyQtPlot/BarWidget.py
PyQtPlot/HistogramWidget.py
PyQtPlot/Plot.py
PyQtPlot/Scatter.py
PyQtPlot/StackedBar.py
PyQtPlot/_Base.py
PyQtPlot/__init__.py
PyQtPlot-0.0.4.3.dist-info/LICENSE
PyQtPlot-0.0.4.3.dist-info/METADATA
PyQtPlot-0.0.4.3.dist-info/WHEEL
PyQtPlot-0.0.4.3.dist-info/top_level.txt
PyQtPlot-0.0.4.3.dist-info/RECORD
